.gitignore
README.txt
setup.py
js/__init__.py
js.handlebars.egg-info/PKG-INFO
js.handlebars.egg-info/SOURCES.txt
js.handlebars.egg-info/dependency_links.txt
js.handlebars.egg-info/entry_points.txt
js.handlebars.egg-info/namespace_packages.txt
js.handlebars.egg-info/not-zip-safe
js.handlebars.egg-info/requires.txt
js.handlebars.egg-info/top_level.txt
js/handlebars/__init__.py
js/handlebars/resources/handlebars.js
js/handlebars/resources/handlebars.runtime.js