Metadata-Version: 1.0
Name: js.handlebars
Version: 1.3.0
Summary: Fanstatic package for Handlebars.js
Home-page: http://github.com/mgood/js.handlebars/
Author: Matt Good
Author-email: matt@matt-good.net
License: BSD
Platform: any
